audiosample/__init__.py
audiosample/audio_48k_10.wav
audiosample/audio_8k_mulaw.wav
audiosample/audiosample.py
audiosample/av_plugins.py
audiosample/downsampler.notworking.py
audiosample/http_file.py
audiosample/mulaw_converter.py
audiosample/notebook.py
audiosample/np_plugins.py
audiosample/play.py
audiosample/play2.py
audiosample/plugins.py
audiosample/notebook_js/spectrogram-player.js
audiosample-2.2.12.dist-info/licenses/LICENSE
audiosample-2.2.12.dist-info/METADATA
audiosample-2.2.12.dist-info/WHEEL
audiosample-2.2.12.dist-info/top_level.txt
audiosample-2.2.12.dist-info/RECORD
